containerlog/__init__.py
containerlog/contextvars.py
containerlog/proxy/__init__.py
containerlog/proxy/std.py
containerlog/py.typed
containerlog/types.py
containerlog-0.4.2.dist-info/LICENSE
containerlog-0.4.2.dist-info/WHEEL
containerlog-0.4.2.dist-info/METADATA
containerlog-0.4.2.dist-info/RECORD
