Metadata-Version: 2.1
Name: containerlog
Version: 0.4.2
Summary: Optimized, opinionated structured logging for Python
Home-page: https://github.com/vapor-ware/containerlog
License: GPL-3.0-or-later
Keywords: logging,structured,optimized
Author: Erick Daniszewski
Author-email: erick@vapor.io
Requires-Python: >=3.6.1,<4.0.0
Classifier: Intended Audience :: Developers
Classifier: License :: OSI Approved :: GNU General Public License v3 (GPLv3)
Classifier: License :: OSI Approved :: GNU General Public License v3 or later (GPLv3+)
Classifier: Operating System :: OS Independent
Classifier: Programming Language :: Python :: 3
Classifier: Programming Language :: Python :: 3.7
Classifier: Programming Language :: Python :: 3.8
Classifier: Programming Language :: Python :: 3.9
Project-URL: Documentation, https://containerlog.readthedocs.io/en/latest/
Project-URL: Repository, https://github.com/vapor-ware/containerlog
